Metadata-Version: 2.1
Name: thencon
Version: 0.1
Summary: Thai-English keyboard converter(Keyboard layout) by ADR
Home-page: https://github.com/RafaFT1150/thencon
Author: ADR
Author-email: anapatdr@icloud.com
License: MIT
Download-URL: https://github.com/RafaFT1150/thencon/archive/refs/tags/v0.1.zip
Keywords: Keyboard,Thai,English,Thai-English,Converter,Keyboard converter,Thai-English keyboard converter,English-Thai keyboard converter
Platform: UNKNOWN
Classifier: Development Status :: 3 - Alpha
Classifier: Intended Audience :: Developers
Classifier: Topic :: Software Development :: Build Tools
Classifier: License :: OSI Approved :: MIT License
Classifier: Programming Language :: Python :: 3
Classifier: Programming Language :: Python :: 3.4
Classifier: Programming Language :: Python :: 3.5
Classifier: Programming Language :: Python :: 3.6
Classifier: Programming Language :: Python :: 3.7
Classifier: Programming Language :: Python :: 3.8
Classifier: Programming Language :: Python :: 3.9
License-File: LICENSE
License-File: LICENSE.txt
